<XtraSerializer version="1.0" application="DataLayoutControl">
  <property name="#LayoutVersion" />
  <property name="OptionsFocus" isnull="true" iskey="true">
    <property name="ActivateSelectedControlOnGotFocus">true</property>
    <property name="AllowFocusControlOnLabelClick">false</property>
    <property name="EnableAutoTabOrder">true</property>
    <property name="AllowFocusControlOnActivatedTabPage">false</property>
    <property name="AllowFocusGroups">true</property>
    <property name="AllowFocusTabbedGroups">true</property>
    <property name="AllowFocusReadonlyEditors">true</property>
    <property name="MoveFocusRightToLeft">false</property>
    <property name="MoveFocusDirection">AcrossThenDown</property>
  </property>
  <property name="LookAndFeel" isnull="true" iskey="true">
    <property name="SkinName">DevExpress Style</property>
    <property name="Style">Skin</property>
    <property name="UseDefaultLookAndFeel">true</property>
    <property name="UseWindowsXPTheme">false</property>
  </property>
  <property name="Items" iskey="true" value="13">
    <property name="Item1" isnull="true" iskey="true">
      <property name="TypeName">LayoutGroup</property>
      <property name="TabbedGroupParentName" />
      <property name="GroupBordersVisible">false</property>
      <property name="AllowDrawBackground">true</property>
      <property name="EnableIndentsWithoutBorders">True</property>
      <property name="OptionsItemText" isnull="true" iskey="true">
        <property name="TextToControlDistance">3</property>
        <property name="TextAlignMode">UseParentOptions</property>
      </property>
      <property name="CaptionImageVisible">true</property>
      <property name="FlowDirection">LeftToRight</property>
      <property name="LayoutMode">Regular</property>
      <property name="CaptionImageLocation">Default</property>
      <property name="CaptionImageIndex">-1</property>
      <property name="AllowBorderColorBlending">false</property>
      <property name="ExpandOnDoubleClick">false</property>
      <property name="Expanded">true</property>
      <property name="DefaultLayoutType">Vertical</property>
      <property name="ShowTabPageCloseButton">false</property>
      <property name="AllowHtmlStringInCaption">false</property>
      <property name="AllowGlyphSkinning">Default</property>
      <property name="OptionsPrint" isnull="true" iskey="true">
        <property name="AppearanceGroupCaption" isnull="true" iskey="true">
          <property name="ForeColor" />
          <property name="BorderColor" />
          <property name="BackColor" />
          <property name="BackColor2" />
          <property name="Font">Tahoma, 8.25pt</property>
          <property name="GradientMode">Horizontal</property>
          <property name="FontSizeDelta">0</property>
          <property name="FontStyleDelta">Regular</property>
        </property>
        <property name="AllowPrintGroupCaption">true</property>
        <property name="TextToControlDistance">-1</property>
        <property name="AllowPrint">true</property>
        <property name="AppearanceItemCaption" isnull="true" iskey="true">
          <property name="ForeColor" />
          <property name="BorderColor" />
          <property name="BackColor" />
          <property name="BackColor2" />
          <property name="Font">Tahoma, 8.25pt</property>
          <property name="GradientMode">Horizontal</property>
          <property name="FontSizeDelta">0</property>
          <property name="FontStyleDelta">Regular</property>
        </property>
      </property>
      <property name="OptionsTableLayoutGroup" isnull="true" iskey="true">
        <property name="RowDefinitions" iskey="true" value="0" />
        <property name="ColumnDefinitions" iskey="true" value="0" />
      </property>
      <property name="Size">@3,Width=390@3,Height=190</property>
      <property name="ExpandButtonVisible">false</property>
      <property name="ExpandButtonMode">Normal</property>
      <property name="HeaderButtonsLocation">Default</property>
      <property name="TextToControlDistance">0</property>
      <property name="TextLocation">Top</property>
      <property name="AppearanceTabPage" isnull="true" iskey="true">
        <property name="Header" isnull="true" iskey="true">
          <property name="ForeColor" />
          <property name="BorderColor" />
          <property name="BackColor" />
          <property name="BackColor2" />
          <property name="Font">Tahoma, 8.25pt</property>
          <property name="GradientMode">Horizontal</property>
          <property name="FontSizeDelta">0</property>
          <property name="FontStyleDelta">Regular</property>
        </property>
        <property name="HeaderActive" isnull="true" iskey="true">
          <property name="ForeColor" />
          <property name="BorderColor" />
          <property name="BackColor" />
          <property name="BackColor2" />
          <property name="Font">Tahoma, 8.25pt</property>
          <property name="GradientMode">Horizontal</property>
          <property name="FontSizeDelta">0</property>
          <property name="FontStyleDelta">Regular</property>
        </property>
        <property name="HeaderDisabled" isnull="true" iskey="true">
          <property name="ForeColor" />
          <property name="BorderColor" />
          <property name="BackColor" />
          <property name="BackColor2" />
          <property name="Font">Tahoma, 8.25pt</property>
          <property name="GradientMode">Horizontal</property>
          <property name="FontSizeDelta">0</property>
          <property name="FontStyleDelta">Regular</property>
        </property>
        <property name="HeaderHotTracked" isnull="true" iskey="true">
          <property name="ForeColor" />
          <property name="BorderColor" />
          <property name="BackColor" />
          <property name="BackColor2" />
          <property name="Font">Tahoma, 8.25pt</property>
          <property name="GradientMode">Horizontal</property>
          <property name="FontSizeDelta">0</property>
          <property name="FontStyleDelta">Regular</property>
        </property>
        <property name="PageClient" isnull="true" iskey="true">
          <property name="ForeColor" />
          <property name="BorderColor" />
          <property name="BackColor" />
          <property name="BackColor2" />
          <property name="Font">Tahoma, 8.25pt</property>
          <property name="GradientMode">Horizontal</property>
          <property name="FontSizeDelta">0</property>
          <property name="FontStyleDelta">Regular</property>
        </property>
      </property>
      <property name="AppearanceGroup" isnull="true" iskey="true">
        <property name="ForeColor" />
        <property name="BorderColor" />
        <property name="BackColor" />
        <property name="BackColor2" />
        <property name="Font">Tahoma, 8.25pt</property>
        <property name="GradientMode">Horizontal</property>
        <property name="FontSizeDelta">0</property>
        <property name="FontStyleDelta">Regular</property>
      </property>
      <property name="TabPageWidth">0</property>
      <property name="OptionsCustomization" isnull="true" iskey="true">
        <property name="AllowDrag">Default</property>
        <property name="AllowDrop">Default</property>
      </property>
      <property name="OptionsTableLayoutItem" isnull="true" iskey="true">
        <property name="RowIndex">0</property>
        <property name="RowSpan">1</property>
        <property name="ColumnIndex">0</property>
        <property name="ColumnSpan">1</property>
      </property>
      <property name="OptionsToolTip" isnull="true" iskey="true">
        <property name="ToolTip" />
        <property name="ToolTipTitle" />
        <property name="ToolTipIconType">None</property>
        <property name="ImmediateToolTip">false</property>
        <property name="AllowHtmlString">Default</property>
        <property name="IconToolTip" />
        <property name="IconToolTipTitle" />
        <property name="IconToolTipIconType">None</property>
        <property name="EnableIconToolTip">true</property>
        <property name="IconImmediateToolTip">false</property>
        <property name="IconAllowHtmlString">Default</property>
      </property>
      <property name="Name">Root</property>
      <property name="AppearanceItemCaption" isnull="true" iskey="true">
        <property name="ForeColor" />
        <property name="BorderColor" />
        <property name="BackColor" />
        <property name="BackColor2" />
        <property name="Font">Tahoma, 8.25pt</property>
        <property name="GradientMode">Horizontal</property>
        <property name="FontSizeDelta">0</property>
        <property name="FontStyleDelta">Regular</property>
      </property>
      <property name="ParentName" />
      <property name="TextVisible">true</property>
      <property name="Spacing">0, 0, 0, 0</property>
      <property name="Padding">10, 10, 10, 10</property>
      <property name="Location">@1,X=0@1,Y=0</property>
      <property name="ShowInCustomizationForm">true</property>
      <property name="Text">Root</property>
      <property name="CustomizationFormText">Root</property>
      <property name="StartNewLine">false</property>
      <property name="Visibility">Always</property>
    </property>
    <property name="Item2" isnull="true" iskey="true">
      <property name="TypeName">LayoutGroup</property>
      <property name="TabbedGroupParentName" />
      <property name="GroupBordersVisible">false</property>
      <property name="AllowDrawBackground">false</property>
      <property name="EnableIndentsWithoutBorders">Default</property>
      <property name="OptionsItemText" isnull="true" iskey="true">
        <property name="TextToControlDistance">3</property>
        <property name="TextAlignMode">UseParentOptions</property>
      </property>
      <property name="CaptionImageVisible">true</property>
      <property name="FlowDirection">LeftToRight</property>
      <property name="LayoutMode">Regular</property>
      <property name="CaptionImageLocation">Default</property>
      <property name="CaptionImageIndex">-1</property>
      <property name="AllowBorderColorBlending">false</property>
      <property name="ExpandOnDoubleClick">false</property>
      <property name="Expanded">true</property>
      <property name="DefaultLayoutType">Vertical</property>
      <property name="ShowTabPageCloseButton">false</property>
      <property name="AllowHtmlStringInCaption">false</property>
      <property name="AllowGlyphSkinning">Default</property>
      <property name="OptionsPrint" isnull="true" iskey="true">
        <property name="AppearanceGroupCaption" isnull="true" iskey="true">
          <property name="ForeColor" />
          <property name="BorderColor" />
          <property name="BackColor" />
          <property name="BackColor2" />
          <property name="Font">Tahoma, 8.25pt</property>
          <property name="GradientMode">Horizontal</property>
          <property name="FontSizeDelta">0</property>
          <property name="FontStyleDelta">Regular</property>
        </property>
        <property name="AllowPrintGroupCaption">true</property>
        <property name="TextToControlDistance">-1</property>
        <property name="AllowPrint">true</property>
        <property name="AppearanceItemCaption" isnull="true" iskey="true">
          <property name="ForeColor" />
          <property name="BorderColor" />
          <property name="BackColor" />
          <property name="BackColor2" />
          <property name="Font">Tahoma, 8.25pt</property>
          <property name="GradientMode">Horizontal</property>
          <property name="FontSizeDelta">0</property>
          <property name="FontStyleDelta">Regular</property>
        </property>
      </property>
      <property name="OptionsTableLayoutGroup" isnull="true" iskey="true">
        <property name="RowDefinitions" iskey="true" value="0" />
        <property name="ColumnDefinitions" iskey="true" value="0" />
      </property>
      <property name="Size">@3,Width=370@3,Height=170</property>
      <property name="ExpandButtonVisible">false</property>
      <property name="ExpandButtonMode">Normal</property>
      <property name="HeaderButtonsLocation">Default</property>
      <property name="TextToControlDistance">0</property>
      <property name="TextLocation">Top</property>
      <property name="AppearanceTabPage" isnull="true" iskey="true">
        <property name="Header" isnull="true" iskey="true">
          <property name="ForeColor" />
          <property name="BorderColor" />
          <property name="BackColor" />
          <property name="BackColor2" />
          <property name="Font">Tahoma, 8.25pt</property>
          <property name="GradientMode">Horizontal</property>
          <property name="FontSizeDelta">0</property>
          <property name="FontStyleDelta">Regular</property>
        </property>
        <property name="HeaderActive" isnull="true" iskey="true">
          <property name="ForeColor" />
          <property name="BorderColor" />
          <property name="BackColor" />
          <property name="BackColor2" />
          <property name="Font">Tahoma, 8.25pt</property>
          <property name="GradientMode">Horizontal</property>
          <property name="FontSizeDelta">0</property>
          <property name="FontStyleDelta">Regular</property>
        </property>
        <property name="HeaderDisabled" isnull="true" iskey="true">
          <property name="ForeColor" />
          <property name="BorderColor" />
          <property name="BackColor" />
          <property name="BackColor2" />
          <property name="Font">Tahoma, 8.25pt</property>
          <property name="GradientMode">Horizontal</property>
          <property name="FontSizeDelta">0</property>
          <property name="FontStyleDelta">Regular</property>
        </property>
        <property name="HeaderHotTracked" isnull="true" iskey="true">
          <property name="ForeColor" />
          <property name="BorderColor" />
          <property name="BackColor" />
          <property name="BackColor2" />
          <property name="Font">Tahoma, 8.25pt</property>
          <property name="GradientMode">Horizontal</property>
          <property name="FontSizeDelta">0</property>
          <property name="FontStyleDelta">Regular</property>
        </property>
        <property name="PageClient" isnull="true" iskey="true">
          <property name="ForeColor" />
          <property name="BorderColor" />
          <property name="BackColor" />
          <property name="BackColor2" />
          <property name="Font">Tahoma, 8.25pt</property>
          <property name="GradientMode">Horizontal</property>
          <property name="FontSizeDelta">0</property>
          <property name="FontStyleDelta">Regular</property>
        </property>
      </property>
      <property name="AppearanceGroup" isnull="true" iskey="true">
        <property name="ForeColor" />
        <property name="BorderColor" />
        <property name="BackColor" />
        <property name="BackColor2" />
        <property name="Font">Tahoma, 8.25pt</property>
        <property name="GradientMode">Horizontal</property>
        <property name="FontSizeDelta">0</property>
        <property name="FontStyleDelta">Regular</property>
      </property>
      <property name="TabPageWidth">0</property>
      <property name="OptionsCustomization" isnull="true" iskey="true">
        <property name="AllowDrag">Default</property>
        <property name="AllowDrop">Default</property>
      </property>
      <property name="OptionsTableLayoutItem" isnull="true" iskey="true">
        <property name="RowIndex">0</property>
        <property name="RowSpan">1</property>
        <property name="ColumnIndex">0</property>
        <property name="ColumnSpan">1</property>
      </property>
      <property name="OptionsToolTip" isnull="true" iskey="true">
        <property name="ToolTip" />
        <property name="ToolTipTitle" />
        <property name="ToolTipIconType">None</property>
        <property name="ImmediateToolTip">false</property>
        <property name="AllowHtmlString">Default</property>
        <property name="IconToolTip" />
        <property name="IconToolTipTitle" />
        <property name="IconToolTipIconType">None</property>
        <property name="EnableIconToolTip">true</property>
        <property name="IconImmediateToolTip">false</property>
        <property name="IconAllowHtmlString">Default</property>
      </property>
      <property name="Name">autoGeneratedGroup0</property>
      <property name="AppearanceItemCaption" isnull="true" iskey="true">
        <property name="ForeColor" />
        <property name="BorderColor" />
        <property name="BackColor" />
        <property name="BackColor2" />
        <property name="Font">Tahoma, 8.25pt</property>
        <property name="GradientMode">Horizontal</property>
        <property name="FontSizeDelta">0</property>
        <property name="FontStyleDelta">Regular</property>
      </property>
      <property name="ParentName">Root</property>
      <property name="TextVisible">true</property>
      <property name="Spacing">2, 2, 2, 2</property>
      <property name="Padding">10, 10, 10, 10</property>
      <property name="Location">@1,X=0@1,Y=0</property>
      <property name="ShowInCustomizationForm">true</property>
      <property name="Text">autoGeneratedGroup0</property>
      <property name="CustomizationFormText">autoGeneratedGroup0</property>
      <property name="StartNewLine">false</property>
      <property name="Visibility">Always</property>
    </property>
    <property name="Item3" isnull="true" iskey="true">
      <property name="TypeName">EmptySpaceItem</property>
      <property name="TextVisible">false</property>
      <property name="TextToControlDistance">0</property>
      <property name="TextLocation">Default</property>
      <property name="ContentVisible">true</property>
      <property name="HighlightFocusedItem">Default</property>
      <property name="TrimClientAreaToControl">true</property>
      <property name="ControlAlignment">TopLeft</property>
      <property name="Image" isnull="true" />
      <property name="ImageAlignment">MiddleLeft</property>
      <property name="ImageIndex">-1</property>
      <property name="ImageToTextDistance">5</property>
      <property name="MinSize">@2,Width=10@2,Height=10</property>
      <property name="MaxSize">@1,Width=0@1,Height=0</property>
      <property name="ControlName" isnull="true" />
      <property name="AllowHtmlStringInCaption">false</property>
      <property name="TextAlignMode">UseParentOptions</property>
      <property name="SizeConstraintsType">Default</property>
      <property name="OptionsPrint" isnull="true" iskey="true">
        <property name="TextToControlDistance">-1</property>
        <property name="AllowPrint">true</property>
        <property name="AppearanceItemCaption" isnull="true" iskey="true">
          <property name="ForeColor" />
          <property name="BorderColor" />
          <property name="BackColor" />
          <property name="BackColor2" />
          <property name="Font">Tahoma, 8.25pt</property>
          <property name="GradientMode">Horizontal</property>
          <property name="FontSizeDelta">0</property>
          <property name="FontStyleDelta">Regular</property>
        </property>
      </property>
      <property name="AllowGlyphSkinning">Default</property>
      <property name="OptionsCustomization" isnull="true" iskey="true">
        <property name="AllowDrag">Default</property>
        <property name="AllowDrop">Default</property>
      </property>
      <property name="OptionsTableLayoutItem" isnull="true" iskey="true">
        <property name="RowIndex">0</property>
        <property name="RowSpan">1</property>
        <property name="ColumnIndex">0</property>
        <property name="ColumnSpan">1</property>
      </property>
      <property name="OptionsToolTip" isnull="true" iskey="true">
        <property name="ToolTip" />
        <property name="ToolTipTitle" />
        <property name="ToolTipIconType">None</property>
        <property name="ImmediateToolTip">false</property>
        <property name="AllowHtmlString">Default</property>
        <property name="IconToolTip" />
        <property name="IconToolTipTitle" />
        <property name="IconToolTipIconType">None</property>
        <property name="EnableIconToolTip">true</property>
        <property name="IconImmediateToolTip">false</property>
        <property name="IconAllowHtmlString">Default</property>
      </property>
      <property name="Name">item0</property>
      <property name="AppearanceItemCaption" isnull="true" iskey="true">
        <property name="ForeColor" />
        <property name="BorderColor" />
        <property name="BackColor" />
        <property name="BackColor2" />
        <property name="Font">Tahoma, 8.25pt</property>
        <property name="GradientMode">Horizontal</property>
        <property name="FontSizeDelta">0</property>
        <property name="FontStyleDelta">Regular</property>
      </property>
      <property name="ParentName">autoGeneratedGroup0</property>
      <property name="TextSize">@1,Width=0@1,Height=0</property>
      <property name="Spacing">0, 0, 0, 0</property>
      <property name="Padding">2, 2, 2, 2</property>
      <property name="Location">@1,X=0@3,Y=131</property>
      <property name="Size">@3,Width=370@2,Height=39</property>
      <property name="ShowInCustomizationForm">true</property>
      <property name="Text">item0</property>
      <property name="CustomizationFormText">item0</property>
      <property name="StartNewLine">false</property>
      <property name="Visibility">Always</property>
    </property>
    <property name="Item4" isnull="true" iskey="true">
      <property name="TypeName">LayoutGroup</property>
      <property name="TabbedGroupParentName" />
      <property name="GroupBordersVisible">true</property>
      <property name="AllowDrawBackground">true</property>
      <property name="EnableIndentsWithoutBorders">Default</property>
      <property name="OptionsItemText" isnull="true" iskey="true">
        <property name="TextToControlDistance">3</property>
        <property name="TextAlignMode">UseParentOptions</property>
      </property>
      <property name="CaptionImageVisible">true</property>
      <property name="FlowDirection">LeftToRight</property>
      <property name="LayoutMode">Regular</property>
      <property name="CaptionImageLocation">Default</property>
      <property name="CaptionImageIndex">-1</property>
      <property name="AllowBorderColorBlending">false</property>
      <property name="ExpandOnDoubleClick">false</property>
      <property name="Expanded">true</property>
      <property name="DefaultLayoutType">Vertical</property>
      <property name="ShowTabPageCloseButton">false</property>
      <property name="AllowHtmlStringInCaption">false</property>
      <property name="AllowGlyphSkinning">Default</property>
      <property name="OptionsPrint" isnull="true" iskey="true">
        <property name="AppearanceGroupCaption" isnull="true" iskey="true">
          <property name="ForeColor" />
          <property name="BorderColor" />
          <property name="BackColor" />
          <property name="BackColor2" />
          <property name="Font">Tahoma, 8.25pt</property>
          <property name="GradientMode">Horizontal</property>
          <property name="FontSizeDelta">0</property>
          <property name="FontStyleDelta">Regular</property>
        </property>
        <property name="AllowPrintGroupCaption">true</property>
        <property name="TextToControlDistance">-1</property>
        <property name="AllowPrint">true</property>
        <property name="AppearanceItemCaption" isnull="true" iskey="true">
          <property name="ForeColor" />
          <property name="BorderColor" />
          <property name="BackColor" />
          <property name="BackColor2" />
          <property name="Font">Tahoma, 8.25pt</property>
          <property name="GradientMode">Horizontal</property>
          <property name="FontSizeDelta">0</property>
          <property name="FontStyleDelta">Regular</property>
        </property>
      </property>
      <property name="OptionsTableLayoutGroup" isnull="true" iskey="true">
        <property name="RowDefinitions" iskey="true" value="0" />
        <property name="ColumnDefinitions" iskey="true" value="0" />
      </property>
      <property name="Size">@3,Width=370@2,Height=66</property>
      <property name="ExpandButtonVisible">false</property>
      <property name="ExpandButtonMode">Normal</property>
      <property name="HeaderButtonsLocation">Default</property>
      <property name="TextToControlDistance">0</property>
      <property name="TextLocation">Top</property>
      <property name="AppearanceTabPage" isnull="true" iskey="true">
        <property name="Header" isnull="true" iskey="true">
          <property name="ForeColor" />
          <property name="BorderColor" />
          <property name="BackColor" />
          <property name="BackColor2" />
          <property name="Font">Tahoma, 8.25pt</property>
          <property name="GradientMode">Horizontal</property>
          <property name="FontSizeDelta">0</property>
          <property name="FontStyleDelta">Regular</property>
        </property>
        <property name="HeaderActive" isnull="true" iskey="true">
          <property name="ForeColor" />
          <property name="BorderColor" />
          <property name="BackColor" />
          <property name="BackColor2" />
          <property name="Font">Tahoma, 8.25pt</property>
          <property name="GradientMode">Horizontal</property>
          <property name="FontSizeDelta">0</property>
          <property name="FontStyleDelta">Regular</property>
        </property>
        <property name="HeaderDisabled" isnull="true" iskey="true">
          <property name="ForeColor" />
          <property name="BorderColor" />
          <property name="BackColor" />
          <property name="BackColor2" />
          <property name="Font">Tahoma, 8.25pt</property>
          <property name="GradientMode">Horizontal</property>
          <property name="FontSizeDelta">0</property>
          <property name="FontStyleDelta">Regular</property>
        </property>
        <property name="HeaderHotTracked" isnull="true" iskey="true">
          <property name="ForeColor" />
          <property name="BorderColor" />
          <property name="BackColor" />
          <property name="BackColor2" />
          <property name="Font">Tahoma, 8.25pt</property>
          <property name="GradientMode">Horizontal</property>
          <property name="FontSizeDelta">0</property>
          <property name="FontStyleDelta">Regular</property>
        </property>
        <property name="PageClient" isnull="true" iskey="true">
          <property name="ForeColor" />
          <property name="BorderColor" />
          <property name="BackColor" />
          <property name="BackColor2" />
          <property name="Font">Tahoma, 8.25pt</property>
          <property name="GradientMode">Horizontal</property>
          <property name="FontSizeDelta">0</property>
          <property name="FontStyleDelta">Regular</property>
        </property>
      </property>
      <property name="AppearanceGroup" isnull="true" iskey="true">
        <property name="ForeColor" />
        <property name="BorderColor" />
        <property name="BackColor" />
        <property name="BackColor2" />
        <property name="Font">Tahoma, 8.25pt</property>
        <property name="GradientMode">Horizontal</property>
        <property name="FontSizeDelta">0</property>
        <property name="FontStyleDelta">Regular</property>
      </property>
      <property name="TabPageWidth">0</property>
      <property name="OptionsCustomization" isnull="true" iskey="true">
        <property name="AllowDrag">Default</property>
        <property name="AllowDrop">Default</property>
      </property>
      <property name="OptionsTableLayoutItem" isnull="true" iskey="true">
        <property name="RowIndex">0</property>
        <property name="RowSpan">1</property>
        <property name="ColumnIndex">0</property>
        <property name="ColumnSpan">1</property>
      </property>
      <property name="OptionsToolTip" isnull="true" iskey="true">
        <property name="ToolTip" />
        <property name="ToolTipTitle" />
        <property name="ToolTipIconType">None</property>
        <property name="ImmediateToolTip">false</property>
        <property name="AllowHtmlString">Default</property>
        <property name="IconToolTip" />
        <property name="IconToolTipTitle" />
        <property name="IconToolTipIconType">None</property>
        <property name="EnableIconToolTip">true</property>
        <property name="IconImmediateToolTip">false</property>
        <property name="IconAllowHtmlString">Default</property>
      </property>
      <property name="Name">item1</property>
      <property name="AppearanceItemCaption" isnull="true" iskey="true">
        <property name="ForeColor" />
        <property name="BorderColor" />
        <property name="BackColor" />
        <property name="BackColor2" />
        <property name="Font">Tahoma, 8.25pt</property>
        <property name="GradientMode">Horizontal</property>
        <property name="FontSizeDelta">0</property>
        <property name="FontStyleDelta">Regular</property>
      </property>
      <property name="ParentName">autoGeneratedGroup0</property>
      <property name="TextVisible">true</property>
      <property name="Spacing">2, 2, 2, 2</property>
      <property name="Padding">9, 9, 9, 9</property>
      <property name="Location">@1,X=0@2,Y=65</property>
      <property name="ShowInCustomizationForm">true</property>
      <property name="Text">Fuzzy</property>
      <property name="CustomizationFormText">item1</property>
      <property name="StartNewLine">false</property>
      <property name="Visibility">Always</property>
    </property>
    <property name="Item5" isnull="true" iskey="true">
      <property name="TypeName">LayoutControlItem</property>
      <property name="ControlName">varCheckEdit</property>
      <property name="AllowHtmlStringInCaption">false</property>
      <property name="TextAlignMode">CustomSize</property>
      <property name="SizeConstraintsType">Custom</property>
      <property name="Image" isnull="true" />
      <property name="ImageIndex">-1</property>
      <property name="ImageAlignment">MiddleLeft</property>
      <property name="ImageToTextDistance">5</property>
      <property name="OptionsPrint" isnull="true" iskey="true">
        <property name="TextToControlDistance">-1</property>
        <property name="AllowPrint">true</property>
        <property name="AppearanceItemCaption" isnull="true" iskey="true">
          <property name="ForeColor" />
          <property name="BorderColor" />
          <property name="BackColor" />
          <property name="BackColor2" />
          <property name="Font">Tahoma, 8.25pt</property>
          <property name="GradientMode">Horizontal</property>
          <property name="FontSizeDelta">0</property>
          <property name="FontStyleDelta">Regular</property>
        </property>
      </property>
      <property name="MaxSize">@1,Width=0@2,Height=23</property>
      <property name="MinSize">@2,Width=57@2,Height=23</property>
      <property name="ControlAlignment">TopLeft</property>
      <property name="ContentVisible">true</property>
      <property name="HighlightFocusedItem">Default</property>
      <property name="TrimClientAreaToControl">true</property>
      <property name="AllowGlyphSkinning">Default</property>
      <property name="OptionsCustomization" isnull="true" iskey="true">
        <property name="AllowDrag">Default</property>
        <property name="AllowDrop">Default</property>
      </property>
      <property name="OptionsTableLayoutItem" isnull="true" iskey="true">
        <property name="RowIndex">0</property>
        <property name="RowSpan">1</property>
        <property name="ColumnIndex">0</property>
        <property name="ColumnSpan">1</property>
      </property>
      <property name="OptionsToolTip" isnull="true" iskey="true">
        <property name="ToolTip" />
        <property name="ToolTipTitle" />
        <property name="ToolTipIconType">None</property>
        <property name="ImmediateToolTip">false</property>
        <property name="AllowHtmlString">Default</property>
        <property name="IconToolTip" />
        <property name="IconToolTipTitle" />
        <property name="IconToolTipIconType">None</property>
        <property name="EnableIconToolTip">true</property>
        <property name="IconImmediateToolTip">false</property>
        <property name="IconAllowHtmlString">Default</property>
      </property>
      <property name="Name">ItemForvar</property>
      <property name="AppearanceItemCaption" isnull="true" iskey="true">
        <property name="ForeColor" />
        <property name="BorderColor" />
        <property name="BackColor" />
        <property name="BackColor2" />
        <property name="Font">Tahoma, 8.25pt</property>
        <property name="GradientMode">Horizontal</property>
        <property name="FontSizeDelta">0</property>
        <property name="FontStyleDelta">Regular</property>
      </property>
      <property name="ParentName">item1</property>
      <property name="TextVisible">false</property>
      <property name="TextSize">@1,Width=0@1,Height=0</property>
      <property name="TextToControlDistance">0</property>
      <property name="Spacing">0, 0, 0, 0</property>
      <property name="Padding">2, 2, 2, 2</property>
      <property name="Location">@1,X=0@1,Y=0</property>
      <property name="Size">@2,Width=57@2,Height=24</property>
      <property name="ShowInCustomizationForm">true</property>
      <property name="Text">Attiva</property>
      <property name="CustomizationFormText">Attiva</property>
      <property name="StartNewLine">false</property>
      <property name="Visibility">Always</property>
      <property name="TextLocation">Left</property>
    </property>
    <property name="Item6" isnull="true" iskey="true">
      <property name="TypeName">LayoutControlItem</property>
      <property name="ControlName">var1TextEdit</property>
      <property name="AllowHtmlStringInCaption">false</property>
      <property name="TextAlignMode">CustomSize</property>
      <property name="SizeConstraintsType">Custom</property>
      <property name="Image" isnull="true" />
      <property name="ImageIndex">-1</property>
      <property name="ImageAlignment">MiddleLeft</property>
      <property name="ImageToTextDistance">5</property>
      <property name="OptionsPrint" isnull="true" iskey="true">
        <property name="TextToControlDistance">-1</property>
        <property name="AllowPrint">true</property>
        <property name="AppearanceItemCaption" isnull="true" iskey="true">
          <property name="ForeColor" />
          <property name="BorderColor" />
          <property name="BackColor" />
          <property name="BackColor2" />
          <property name="Font">Tahoma, 8.25pt</property>
          <property name="GradientMode">Horizontal</property>
          <property name="FontSizeDelta">0</property>
          <property name="FontStyleDelta">Regular</property>
        </property>
      </property>
      <property name="MaxSize">@1,Width=0@2,Height=24</property>
      <property name="MinSize">@2,Width=86@2,Height=24</property>
      <property name="ControlAlignment">TopLeft</property>
      <property name="ContentVisible">true</property>
      <property name="HighlightFocusedItem">Default</property>
      <property name="TrimClientAreaToControl">true</property>
      <property name="AllowGlyphSkinning">Default</property>
      <property name="OptionsCustomization" isnull="true" iskey="true">
        <property name="AllowDrag">Default</property>
        <property name="AllowDrop">Default</property>
      </property>
      <property name="OptionsTableLayoutItem" isnull="true" iskey="true">
        <property name="RowIndex">0</property>
        <property name="RowSpan">1</property>
        <property name="ColumnIndex">0</property>
        <property name="ColumnSpan">1</property>
      </property>
      <property name="OptionsToolTip" isnull="true" iskey="true">
        <property name="ToolTip" />
        <property name="ToolTipTitle" />
        <property name="ToolTipIconType">None</property>
        <property name="ImmediateToolTip">false</property>
        <property name="AllowHtmlString">Default</property>
        <property name="IconToolTip" />
        <property name="IconToolTipTitle" />
        <property name="IconToolTipIconType">None</property>
        <property name="EnableIconToolTip">true</property>
        <property name="IconImmediateToolTip">false</property>
        <property name="IconAllowHtmlString">Default</property>
      </property>
      <property name="Name">ItemForvar1</property>
      <property name="AppearanceItemCaption" isnull="true" iskey="true">
        <property name="ForeColor" />
        <property name="BorderColor" />
        <property name="BackColor" />
        <property name="BackColor2" />
        <property name="Font">Tahoma, 8.25pt</property>
        <property name="GradientMode">Horizontal</property>
        <property name="FontSizeDelta">0</property>
        <property name="FontStyleDelta">Regular</property>
      </property>
      <property name="ParentName">item1</property>
      <property name="TextVisible">true</property>
      <property name="TextSize">@2,Width=40@2,Height=13</property>
      <property name="TextToControlDistance">5</property>
      <property name="Spacing">0, 0, 0, 0</property>
      <property name="Padding">2, 2, 2, 2</property>
      <property name="Location">@2,X=57@1,Y=0</property>
      <property name="Size">@2,Width=86@2,Height=24</property>
      <property name="ShowInCustomizationForm">true</property>
      <property name="Text">Prefisso</property>
      <property name="CustomizationFormText">Prefisso</property>
      <property name="StartNewLine">false</property>
      <property name="Visibility">Always</property>
      <property name="TextLocation">Default</property>
    </property>
    <property name="Item7" isnull="true" iskey="true">
      <property name="TypeName">LayoutControlItem</property>
      <property name="ControlName">var2TextEdit</property>
      <property name="AllowHtmlStringInCaption">false</property>
      <property name="TextAlignMode">UseParentOptions</property>
      <property name="SizeConstraintsType">Default</property>
      <property name="Image" isnull="true" />
      <property name="ImageIndex">-1</property>
      <property name="ImageAlignment">MiddleLeft</property>
      <property name="ImageToTextDistance">5</property>
      <property name="OptionsPrint" isnull="true" iskey="true">
        <property name="TextToControlDistance">-1</property>
        <property name="AllowPrint">true</property>
        <property name="AppearanceItemCaption" isnull="true" iskey="true">
          <property name="ForeColor" />
          <property name="BorderColor" />
          <property name="BackColor" />
          <property name="BackColor2" />
          <property name="Font">Tahoma, 8.25pt</property>
          <property name="GradientMode">Horizontal</property>
          <property name="FontSizeDelta">0</property>
          <property name="FontStyleDelta">Regular</property>
        </property>
      </property>
      <property name="MaxSize">@1,Width=0@2,Height=24</property>
      <property name="MinSize">@2,Width=54@2,Height=24</property>
      <property name="ControlAlignment">TopLeft</property>
      <property name="ContentVisible">true</property>
      <property name="HighlightFocusedItem">Default</property>
      <property name="TrimClientAreaToControl">true</property>
      <property name="AllowGlyphSkinning">Default</property>
      <property name="OptionsCustomization" isnull="true" iskey="true">
        <property name="AllowDrag">Default</property>
        <property name="AllowDrop">Default</property>
      </property>
      <property name="OptionsTableLayoutItem" isnull="true" iskey="true">
        <property name="RowIndex">0</property>
        <property name="RowSpan">1</property>
        <property name="ColumnIndex">0</property>
        <property name="ColumnSpan">1</property>
      </property>
      <property name="OptionsToolTip" isnull="true" iskey="true">
        <property name="ToolTip" />
        <property name="ToolTipTitle" />
        <property name="ToolTipIconType">None</property>
        <property name="ImmediateToolTip">false</property>
        <property name="AllowHtmlString">Default</property>
        <property name="IconToolTip" />
        <property name="IconToolTipTitle" />
        <property name="IconToolTipIconType">None</property>
        <property name="EnableIconToolTip">true</property>
        <property name="IconImmediateToolTip">false</property>
        <property name="IconAllowHtmlString">Default</property>
      </property>
      <property name="Name">ItemForvar2</property>
      <property name="AppearanceItemCaption" isnull="true" iskey="true">
        <property name="ForeColor" />
        <property name="BorderColor" />
        <property name="BackColor" />
        <property name="BackColor2" />
        <property name="Font">Tahoma, 8.25pt</property>
        <property name="GradientMode">Horizontal</property>
        <property name="FontSizeDelta">0</property>
        <property name="FontStyleDelta">Regular</property>
      </property>
      <property name="ParentName">item1</property>
      <property name="TextVisible">false</property>
      <property name="TextSize">@1,Width=0@1,Height=0</property>
      <property name="TextToControlDistance">0</property>
      <property name="Spacing">0, 0, 0, 0</property>
      <property name="Padding">2, 2, 2, 2</property>
      <property name="Location">@3,X=228@1,Y=0</property>
      <property name="Size">@2,Width=54@2,Height=24</property>
      <property name="ShowInCustomizationForm">true</property>
      <property name="Text">var2</property>
      <property name="CustomizationFormText">var2</property>
      <property name="StartNewLine">false</property>
      <property name="Visibility">Always</property>
      <property name="TextLocation">Default</property>
    </property>
    <property name="Item8" isnull="true" iskey="true">
      <property name="TypeName">LayoutControlItem</property>
      <property name="ControlName">var3TextEdit</property>
      <property name="AllowHtmlStringInCaption">false</property>
      <property name="TextAlignMode">UseParentOptions</property>
      <property name="SizeConstraintsType">Default</property>
      <property name="Image" isnull="true" />
      <property name="ImageIndex">-1</property>
      <property name="ImageAlignment">MiddleLeft</property>
      <property name="ImageToTextDistance">5</property>
      <property name="OptionsPrint" isnull="true" iskey="true">
        <property name="TextToControlDistance">-1</property>
        <property name="AllowPrint">true</property>
        <property name="AppearanceItemCaption" isnull="true" iskey="true">
          <property name="ForeColor" />
          <property name="BorderColor" />
          <property name="BackColor" />
          <property name="BackColor2" />
          <property name="Font">Tahoma, 8.25pt</property>
          <property name="GradientMode">Horizontal</property>
          <property name="FontSizeDelta">0</property>
          <property name="FontStyleDelta">Regular</property>
        </property>
      </property>
      <property name="MaxSize">@1,Width=0@2,Height=24</property>
      <property name="MinSize">@2,Width=54@2,Height=24</property>
      <property name="ControlAlignment">TopLeft</property>
      <property name="ContentVisible">true</property>
      <property name="HighlightFocusedItem">Default</property>
      <property name="TrimClientAreaToControl">true</property>
      <property name="AllowGlyphSkinning">Default</property>
      <property name="OptionsCustomization" isnull="true" iskey="true">
        <property name="AllowDrag">Default</property>
        <property name="AllowDrop">Default</property>
      </property>
      <property name="OptionsTableLayoutItem" isnull="true" iskey="true">
        <property name="RowIndex">0</property>
        <property name="RowSpan">1</property>
        <property name="ColumnIndex">0</property>
        <property name="ColumnSpan">1</property>
      </property>
      <property name="OptionsToolTip" isnull="true" iskey="true">
        <property name="ToolTip" />
        <property name="ToolTipTitle" />
        <property name="ToolTipIconType">None</property>
        <property name="ImmediateToolTip">false</property>
        <property name="AllowHtmlString">Default</property>
        <property name="IconToolTip" />
        <property name="IconToolTipTitle" />
        <property name="IconToolTipIconType">None</property>
        <property name="EnableIconToolTip">true</property>
        <property name="IconImmediateToolTip">false</property>
        <property name="IconAllowHtmlString">Default</property>
      </property>
      <property name="Name">ItemForvar3</property>
      <property name="AppearanceItemCaption" isnull="true" iskey="true">
        <property name="ForeColor" />
        <property name="BorderColor" />
        <property name="BackColor" />
        <property name="BackColor2" />
        <property name="Font">Tahoma, 8.25pt</property>
        <property name="GradientMode">Horizontal</property>
        <property name="FontSizeDelta">0</property>
        <property name="FontStyleDelta">Regular</property>
      </property>
      <property name="ParentName">item1</property>
      <property name="TextVisible">false</property>
      <property name="TextSize">@1,Width=0@1,Height=0</property>
      <property name="TextToControlDistance">0</property>
      <property name="Spacing">0, 0, 0, 0</property>
      <property name="Padding">2, 2, 2, 2</property>
      <property name="Location">@3,X=292@1,Y=0</property>
      <property name="Size">@2,Width=54@2,Height=24</property>
      <property name="ShowInCustomizationForm">true</property>
      <property name="Text">var3</property>
      <property name="CustomizationFormText">var3</property>
      <property name="StartNewLine">false</property>
      <property name="Visibility">Always</property>
      <property name="TextLocation">Default</property>
    </property>
    <property name="Item9" isnull="true" iskey="true">
      <property name="TextVisible">true</property>
      <property name="TypeName">SimpleLabelItem</property>
      <property name="MinSize">@2,Width=10@2,Height=17</property>
      <property name="MaxSize">@1,Width=0@1,Height=0</property>
      <property name="TextToControlDistance">0</property>
      <property name="TextLocation">Default</property>
      <property name="ContentVisible">true</property>
      <property name="HighlightFocusedItem">Default</property>
      <property name="TrimClientAreaToControl">true</property>
      <property name="ControlAlignment">TopLeft</property>
      <property name="Image" isnull="true" />
      <property name="ImageAlignment">MiddleLeft</property>
      <property name="ImageIndex">-1</property>
      <property name="ImageToTextDistance">5</property>
      <property name="ControlName" isnull="true" />
      <property name="AllowHtmlStringInCaption">false</property>
      <property name="TextAlignMode">UseParentOptions</property>
      <property name="SizeConstraintsType">Custom</property>
      <property name="OptionsPrint" isnull="true" iskey="true">
        <property name="TextToControlDistance">-1</property>
        <property name="AllowPrint">true</property>
        <property name="AppearanceItemCaption" isnull="true" iskey="true">
          <property name="ForeColor" />
          <property name="BorderColor" />
          <property name="BackColor" />
          <property name="BackColor2" />
          <property name="Font">Tahoma, 8.25pt</property>
          <property name="GradientMode">Horizontal</property>
          <property name="FontSizeDelta">0</property>
          <property name="FontStyleDelta">Regular</property>
        </property>
      </property>
      <property name="AllowGlyphSkinning">Default</property>
      <property name="OptionsCustomization" isnull="true" iskey="true">
        <property name="AllowDrag">Default</property>
        <property name="AllowDrop">Default</property>
      </property>
      <property name="OptionsTableLayoutItem" isnull="true" iskey="true">
        <property name="RowIndex">0</property>
        <property name="RowSpan">1</property>
        <property name="ColumnIndex">0</property>
        <property name="ColumnSpan">1</property>
      </property>
      <property name="OptionsToolTip" isnull="true" iskey="true">
        <property name="ToolTip" />
        <property name="ToolTipTitle" />
        <property name="ToolTipIconType">None</property>
        <property name="ImmediateToolTip">false</property>
        <property name="AllowHtmlString">Default</property>
        <property name="IconToolTip" />
        <property name="IconToolTipTitle" />
        <property name="IconToolTipIconType">None</property>
        <property name="EnableIconToolTip">true</property>
        <property name="IconImmediateToolTip">false</property>
        <property name="IconAllowHtmlString">Default</property>
      </property>
      <property name="Name">item3</property>
      <property name="AppearanceItemCaption" isnull="true" iskey="true">
        <property name="ForeColor" />
        <property name="BorderColor" />
        <property name="BackColor" />
        <property name="BackColor2" />
        <property name="Font">Tahoma, 8.25pt</property>
        <property name="GradientMode">Horizontal</property>
        <property name="FontSizeDelta">0</property>
        <property name="FontStyleDelta">Regular</property>
      </property>
      <property name="ParentName">item1</property>
      <property name="TextSize">@2,Width=79@2,Height=13</property>
      <property name="Spacing">0, 0, 0, 0</property>
      <property name="Padding">2, 2, 2, 2</property>
      <property name="Location">@3,X=282@1,Y=0</property>
      <property name="Size">@2,Width=10@2,Height=24</property>
      <property name="ShowInCustomizationForm">true</property>
      <property name="Text">/</property>
      <property name="CustomizationFormText">/</property>
      <property name="StartNewLine">false</property>
      <property name="Visibility">Always</property>
    </property>
    <property name="Item10" isnull="true" iskey="true">
      <property name="TextVisible">true</property>
      <property name="TypeName">SimpleLabelItem</property>
      <property name="MinSize">@2,Width=83@2,Height=17</property>
      <property name="MaxSize">@1,Width=0@2,Height=17</property>
      <property name="TextToControlDistance">0</property>
      <property name="TextLocation">Default</property>
      <property name="ContentVisible">true</property>
      <property name="HighlightFocusedItem">Default</property>
      <property name="TrimClientAreaToControl">true</property>
      <property name="ControlAlignment">TopLeft</property>
      <property name="Image" isnull="true" />
      <property name="ImageAlignment">MiddleLeft</property>
      <property name="ImageIndex">-1</property>
      <property name="ImageToTextDistance">5</property>
      <property name="ControlName" isnull="true" />
      <property name="AllowHtmlStringInCaption">false</property>
      <property name="TextAlignMode">UseParentOptions</property>
      <property name="SizeConstraintsType">Default</property>
      <property name="OptionsPrint" isnull="true" iskey="true">
        <property name="TextToControlDistance">-1</property>
        <property name="AllowPrint">true</property>
        <property name="AppearanceItemCaption" isnull="true" iskey="true">
          <property name="ForeColor" />
          <property name="BorderColor" />
          <property name="BackColor" />
          <property name="BackColor2" />
          <property name="Font">Tahoma, 8.25pt</property>
          <property name="GradientMode">Horizontal</property>
          <property name="FontSizeDelta">0</property>
          <property name="FontStyleDelta">Regular</property>
        </property>
      </property>
      <property name="AllowGlyphSkinning">Default</property>
      <property name="OptionsCustomization" isnull="true" iskey="true">
        <property name="AllowDrag">Default</property>
        <property name="AllowDrop">Default</property>
      </property>
      <property name="OptionsTableLayoutItem" isnull="true" iskey="true">
        <property name="RowIndex">0</property>
        <property name="RowSpan">1</property>
        <property name="ColumnIndex">0</property>
        <property name="ColumnSpan">1</property>
      </property>
      <property name="OptionsToolTip" isnull="true" iskey="true">
        <property name="ToolTip" />
        <property name="ToolTipTitle" />
        <property name="ToolTipIconType">None</property>
        <property name="ImmediateToolTip">false</property>
        <property name="AllowHtmlString">Default</property>
        <property name="IconToolTip" />
        <property name="IconToolTipTitle" />
        <property name="IconToolTipIconType">None</property>
        <property name="EnableIconToolTip">true</property>
        <property name="IconImmediateToolTip">false</property>
        <property name="IconAllowHtmlString">Default</property>
      </property>
      <property name="Name">item4</property>
      <property name="AppearanceItemCaption" isnull="true" iskey="true">
        <property name="ForeColor" />
        <property name="BorderColor" />
        <property name="BackColor" />
        <property name="BackColor2" />
        <property name="Font">Tahoma, 8.25pt</property>
        <property name="GradientMode">Horizontal</property>
        <property name="FontSizeDelta">0</property>
        <property name="FontStyleDelta">Regular</property>
      </property>
      <property name="ParentName">item1</property>
      <property name="TextSize">@2,Width=79@2,Height=13</property>
      <property name="Spacing">0, 0, 0, 0</property>
      <property name="Padding">2, 2, 2, 2</property>
      <property name="Location">@3,X=143@1,Y=0</property>
      <property name="Size">@2,Width=85@2,Height=24</property>
      <property name="ShowInCustomizationForm">true</property>
      <property name="Text">Errori / Caratteri</property>
      <property name="CustomizationFormText">Errori / Caratteri</property>
      <property name="StartNewLine">false</property>
      <property name="Visibility">Always</property>
    </property>
    <property name="Item11" isnull="true" iskey="true">
      <property name="TypeName">LayoutGroup</property>
      <property name="TabbedGroupParentName" />
      <property name="GroupBordersVisible">true</property>
      <property name="AllowDrawBackground">true</property>
      <property name="EnableIndentsWithoutBorders">Default</property>
      <property name="OptionsItemText" isnull="true" iskey="true">
        <property name="TextToControlDistance">3</property>
        <property name="TextAlignMode">UseParentOptions</property>
      </property>
      <property name="CaptionImageVisible">true</property>
      <property name="FlowDirection">LeftToRight</property>
      <property name="LayoutMode">Regular</property>
      <property name="CaptionImageLocation">Default</property>
      <property name="CaptionImageIndex">-1</property>
      <property name="AllowBorderColorBlending">false</property>
      <property name="ExpandOnDoubleClick">false</property>
      <property name="Expanded">true</property>
      <property name="DefaultLayoutType">Vertical</property>
      <property name="ShowTabPageCloseButton">false</property>
      <property name="AllowHtmlStringInCaption">false</property>
      <property name="AllowGlyphSkinning">Default</property>
      <property name="OptionsPrint" isnull="true" iskey="true">
        <property name="AppearanceGroupCaption" isnull="true" iskey="true">
          <property name="ForeColor" />
          <property name="BorderColor" />
          <property name="BackColor" />
          <property name="BackColor2" />
          <property name="Font">Tahoma, 8.25pt</property>
          <property name="GradientMode">Horizontal</property>
          <property name="FontSizeDelta">0</property>
          <property name="FontStyleDelta">Regular</property>
        </property>
        <property name="AllowPrintGroupCaption">true</property>
        <property name="TextToControlDistance">-1</property>
        <property name="AllowPrint">true</property>
        <property name="AppearanceItemCaption" isnull="true" iskey="true">
          <property name="ForeColor" />
          <property name="BorderColor" />
          <property name="BackColor" />
          <property name="BackColor2" />
          <property name="Font">Tahoma, 8.25pt</property>
          <property name="GradientMode">Horizontal</property>
          <property name="FontSizeDelta">0</property>
          <property name="FontStyleDelta">Regular</property>
        </property>
      </property>
      <property name="OptionsTableLayoutGroup" isnull="true" iskey="true">
        <property name="RowDefinitions" iskey="true" value="0" />
        <property name="ColumnDefinitions" iskey="true" value="0" />
      </property>
      <property name="Size">@3,Width=370@2,Height=65</property>
      <property name="ExpandButtonVisible">false</property>
      <property name="ExpandButtonMode">Normal</property>
      <property name="HeaderButtonsLocation">Default</property>
      <property name="TextToControlDistance">0</property>
      <property name="TextLocation">Top</property>
      <property name="AppearanceTabPage" isnull="true" iskey="true">
        <property name="Header" isnull="true" iskey="true">
          <property name="ForeColor" />
          <property name="BorderColor" />
          <property name="BackColor" />
          <property name="BackColor2" />
          <property name="Font">Tahoma, 8.25pt</property>
          <property name="GradientMode">Horizontal</property>
          <property name="FontSizeDelta">0</property>
          <property name="FontStyleDelta">Regular</property>
        </property>
        <property name="HeaderActive" isnull="true" iskey="true">
          <property name="ForeColor" />
          <property name="BorderColor" />
          <property name="BackColor" />
          <property name="BackColor2" />
          <property name="Font">Tahoma, 8.25pt</property>
          <property name="GradientMode">Horizontal</property>
          <property name="FontSizeDelta">0</property>
          <property name="FontStyleDelta">Regular</property>
        </property>
        <property name="HeaderDisabled" isnull="true" iskey="true">
          <property name="ForeColor" />
          <property name="BorderColor" />
          <property name="BackColor" />
          <property name="BackColor2" />
          <property name="Font">Tahoma, 8.25pt</property>
          <property name="GradientMode">Horizontal</property>
          <property name="FontSizeDelta">0</property>
          <property name="FontStyleDelta">Regular</property>
        </property>
        <property name="HeaderHotTracked" isnull="true" iskey="true">
          <property name="ForeColor" />
          <property name="BorderColor" />
          <property name="BackColor" />
          <property name="BackColor2" />
          <property name="Font">Tahoma, 8.25pt</property>
          <property name="GradientMode">Horizontal</property>
          <property name="FontSizeDelta">0</property>
          <property name="FontStyleDelta">Regular</property>
        </property>
        <property name="PageClient" isnull="true" iskey="true">
          <property name="ForeColor" />
          <property name="BorderColor" />
          <property name="BackColor" />
          <property name="BackColor2" />
          <property name="Font">Tahoma, 8.25pt</property>
          <property name="GradientMode">Horizontal</property>
          <property name="FontSizeDelta">0</property>
          <property name="FontStyleDelta">Regular</property>
        </property>
      </property>
      <property name="AppearanceGroup" isnull="true" iskey="true">
        <property name="ForeColor" />
        <property name="BorderColor" />
        <property name="BackColor" />
        <property name="BackColor2" />
        <property name="Font">Tahoma, 8.25pt</property>
        <property name="GradientMode">Horizontal</property>
        <property name="FontSizeDelta">0</property>
        <property name="FontStyleDelta">Regular</property>
      </property>
      <property name="TabPageWidth">0</property>
      <property name="OptionsCustomization" isnull="true" iskey="true">
        <property name="AllowDrag">Default</property>
        <property name="AllowDrop">Default</property>
      </property>
      <property name="OptionsTableLayoutItem" isnull="true" iskey="true">
        <property name="RowIndex">0</property>
        <property name="RowSpan">1</property>
        <property name="ColumnIndex">0</property>
        <property name="ColumnSpan">1</property>
      </property>
      <property name="OptionsToolTip" isnull="true" iskey="true">
        <property name="ToolTip" />
        <property name="ToolTipTitle" />
        <property name="ToolTipIconType">None</property>
        <property name="ImmediateToolTip">false</property>
        <property name="AllowHtmlString">Default</property>
        <property name="IconToolTip" />
        <property name="IconToolTipTitle" />
        <property name="IconToolTipIconType">None</property>
        <property name="EnableIconToolTip">true</property>
        <property name="IconImmediateToolTip">false</property>
        <property name="IconAllowHtmlString">Default</property>
      </property>
      <property name="Name">item2</property>
      <property name="AppearanceItemCaption" isnull="true" iskey="true">
        <property name="ForeColor" />
        <property name="BorderColor" />
        <property name="BackColor" />
        <property name="BackColor2" />
        <property name="Font">Tahoma, 8.25pt</property>
        <property name="GradientMode">Horizontal</property>
        <property name="FontSizeDelta">0</property>
        <property name="FontStyleDelta">Regular</property>
      </property>
      <property name="ParentName">autoGeneratedGroup0</property>
      <property name="TextVisible">true</property>
      <property name="Spacing">2, 2, 2, 2</property>
      <property name="Padding">9, 9, 9, 9</property>
      <property name="Location">@1,X=0@1,Y=0</property>
      <property name="ShowInCustomizationForm">true</property>
      <property name="Text">Maschile / Feminile</property>
      <property name="CustomizationFormText">Maschile / Feminile</property>
      <property name="StartNewLine">false</property>
      <property name="Visibility">Always</property>
    </property>
    <property name="Item12" isnull="true" iskey="true">
      <property name="TypeName">LayoutControlItem</property>
      <property name="ControlName">mfspCheckEdit</property>
      <property name="AllowHtmlStringInCaption">false</property>
      <property name="TextAlignMode">UseParentOptions</property>
      <property name="SizeConstraintsType">Custom</property>
      <property name="Image" isnull="true" />
      <property name="ImageIndex">-1</property>
      <property name="ImageAlignment">MiddleLeft</property>
      <property name="ImageToTextDistance">5</property>
      <property name="OptionsPrint" isnull="true" iskey="true">
        <property name="TextToControlDistance">-1</property>
        <property name="AllowPrint">true</property>
        <property name="AppearanceItemCaption" isnull="true" iskey="true">
          <property name="ForeColor" />
          <property name="BorderColor" />
          <property name="BackColor" />
          <property name="BackColor2" />
          <property name="Font">Tahoma, 8.25pt</property>
          <property name="GradientMode">Horizontal</property>
          <property name="FontSizeDelta">0</property>
          <property name="FontStyleDelta">Regular</property>
        </property>
      </property>
      <property name="MaxSize">@1,Width=0@1,Height=0</property>
      <property name="MinSize">@2,Width=57@2,Height=23</property>
      <property name="ControlAlignment">TopLeft</property>
      <property name="ContentVisible">true</property>
      <property name="HighlightFocusedItem">Default</property>
      <property name="TrimClientAreaToControl">true</property>
      <property name="AllowGlyphSkinning">Default</property>
      <property name="OptionsCustomization" isnull="true" iskey="true">
        <property name="AllowDrag">Default</property>
        <property name="AllowDrop">Default</property>
      </property>
      <property name="OptionsTableLayoutItem" isnull="true" iskey="true">
        <property name="RowIndex">0</property>
        <property name="RowSpan">1</property>
        <property name="ColumnIndex">0</property>
        <property name="ColumnSpan">1</property>
      </property>
      <property name="OptionsToolTip" isnull="true" iskey="true">
        <property name="ToolTip">Attiva estensione Maschile/Feminile</property>
        <property name="ToolTipTitle" />
        <property name="ToolTipIconType">None</property>
        <property name="ImmediateToolTip">false</property>
        <property name="AllowHtmlString">Default</property>
        <property name="IconToolTip" />
        <property name="IconToolTipTitle" />
        <property name="IconToolTipIconType">None</property>
        <property name="EnableIconToolTip">true</property>
        <property name="IconImmediateToolTip">false</property>
        <property name="IconAllowHtmlString">Default</property>
      </property>
      <property name="Name">ItemFormfsp</property>
      <property name="AppearanceItemCaption" isnull="true" iskey="true">
        <property name="ForeColor" />
        <property name="BorderColor" />
        <property name="BackColor" />
        <property name="BackColor2" />
        <property name="Font">Tahoma, 8.25pt</property>
        <property name="GradientMode">Horizontal</property>
        <property name="FontSizeDelta">0</property>
        <property name="FontStyleDelta">Regular</property>
      </property>
      <property name="ParentName">item2</property>
      <property name="TextVisible">false</property>
      <property name="TextSize">@1,Width=0@1,Height=0</property>
      <property name="TextToControlDistance">0</property>
      <property name="Spacing">0, 0, 0, 0</property>
      <property name="Padding">2, 2, 2, 2</property>
      <property name="Location">@1,X=0@1,Y=0</property>
      <property name="Size">@2,Width=57@2,Height=23</property>
      <property name="ShowInCustomizationForm">true</property>
      <property name="Text">Attiva</property>
      <property name="CustomizationFormText">Attiva</property>
      <property name="StartNewLine">false</property>
      <property name="Visibility">Always</property>
      <property name="TextLocation">Left</property>
    </property>
    <property name="Item13" isnull="true" iskey="true">
      <property name="TypeName">EmptySpaceItem</property>
      <property name="TextVisible">false</property>
      <property name="TextToControlDistance">0</property>
      <property name="TextLocation">Default</property>
      <property name="ContentVisible">true</property>
      <property name="HighlightFocusedItem">Default</property>
      <property name="TrimClientAreaToControl">true</property>
      <property name="ControlAlignment">TopLeft</property>
      <property name="Image" isnull="true" />
      <property name="ImageAlignment">MiddleLeft</property>
      <property name="ImageIndex">-1</property>
      <property name="ImageToTextDistance">5</property>
      <property name="MinSize">@2,Width=10@2,Height=10</property>
      <property name="MaxSize">@1,Width=0@1,Height=0</property>
      <property name="ControlName" isnull="true" />
      <property name="AllowHtmlStringInCaption">false</property>
      <property name="TextAlignMode">UseParentOptions</property>
      <property name="SizeConstraintsType">Default</property>
      <property name="OptionsPrint" isnull="true" iskey="true">
        <property name="TextToControlDistance">-1</property>
        <property name="AllowPrint">true</property>
        <property name="AppearanceItemCaption" isnull="true" iskey="true">
          <property name="ForeColor" />
          <property name="BorderColor" />
          <property name="BackColor" />
          <property name="BackColor2" />
          <property name="Font">Tahoma, 8.25pt</property>
          <property name="GradientMode">Horizontal</property>
          <property name="FontSizeDelta">0</property>
          <property name="FontStyleDelta">Regular</property>
        </property>
      </property>
      <property name="AllowGlyphSkinning">Default</property>
      <property name="OptionsCustomization" isnull="true" iskey="true">
        <property name="AllowDrag">Default</property>
        <property name="AllowDrop">Default</property>
      </property>
      <property name="OptionsTableLayoutItem" isnull="true" iskey="true">
        <property name="RowIndex">0</property>
        <property name="RowSpan">1</property>
        <property name="ColumnIndex">0</property>
        <property name="ColumnSpan">1</property>
      </property>
      <property name="OptionsToolTip" isnull="true" iskey="true">
        <property name="ToolTip" />
        <property name="ToolTipTitle" />
        <property name="ToolTipIconType">None</property>
        <property name="ImmediateToolTip">false</property>
        <property name="AllowHtmlString">Default</property>
        <property name="IconToolTip" />
        <property name="IconToolTipTitle" />
        <property name="IconToolTipIconType">None</property>
        <property name="EnableIconToolTip">true</property>
        <property name="IconImmediateToolTip">false</property>
        <property name="IconAllowHtmlString">Default</property>
      </property>
      <property name="Name">item6</property>
      <property name="AppearanceItemCaption" isnull="true" iskey="true">
        <property name="ForeColor" />
        <property name="BorderColor" />
        <property name="BackColor" />
        <property name="BackColor2" />
        <property name="Font">Tahoma, 8.25pt</property>
        <property name="GradientMode">Horizontal</property>
        <property name="FontSizeDelta">0</property>
        <property name="FontStyleDelta">Regular</property>
      </property>
      <property name="ParentName">item2</property>
      <property name="TextSize">@1,Width=0@1,Height=0</property>
      <property name="Spacing">0, 0, 0, 0</property>
      <property name="Padding">2, 2, 2, 2</property>
      <property name="Location">@2,X=57@1,Y=0</property>
      <property name="Size">@3,Width=289@2,Height=23</property>
      <property name="ShowInCustomizationForm">true</property>
      <property name="Text">item6</property>
      <property name="CustomizationFormText">item6</property>
      <property name="StartNewLine">false</property>
      <property name="Visibility">Always</property>
    </property>
  </property>
</XtraSerializer>